SonarQubeScraper
