Metadata-Version: 1.0
Name: jenkins-sonarqubescraper
Version: 4.0.2
Summary: Sonar Qube Scraper for Jenkins
Home-page: https://github.com/KMK-ONLINE/PivotalTrackerScraper
Author: Henry Xu
Author-email: hxu@bbmtek.com
License: MIT
Platform: UNKNOWN
